pystc/__init__.py
pystc/pystc.py
pystc/stc_extension.cpython-312-x86_64-linux-gnu.so
pystcstego-0.1.0.dist-info/LICENSE.txt
pystcstego-0.1.0.dist-info/METADATA
pystcstego-0.1.0.dist-info/WHEEL
pystcstego-0.1.0.dist-info/top_level.txt
pystcstego-0.1.0.dist-info/RECORD
