Metadata-Version: 2.1
Name: pystcstego
Version: 0.1.0
Summary: A Python interface for Syndrome Trellis Codes Steganography
Home-page: https://github.com/daniellerch/pySTC
Author: Daniel Lerch Hostalot
Author-email: dlerch@gmail.com
Classifier: Programming Language :: Python :: 3
Classifier: License :: OSI Approved :: MIT License
Classifier: Operating System :: OS Independent
Requires-Python: >=3.6
License-File: LICENSE.txt
Requires-Dist: numpy
